Workbook

Sheet Despesas 2024
A1: ID | B1: Data | C1: Categoria | D1: Subcategoria | E1: Descrição | F1: Fornecedor | G1: Valor | H1: Departamento | I1: Centro de Custo | J1: Aprovador | K1: Status
A2: 1 | B2: 23/02/2024 | C2: TI | D2: Cloud | E2: Despesa 1 - Cloud | F2: Eta Supplies | G2: 489.33047 | H2: Diretoria | I2: CC-7698 | J2: Pedro Oliveira | K2: Pendente
A3: 2 | B3: 27/04/2024 | C3: Pessoal | D3: Salários | E3: Despesa 2 - Salários | F3: Delta Logistics | G3: 6273.7104 | H3: Diretoria | I3: CC-1141 | J3: Carla Souza | K3: Aprovado
A4: 3 | B4: 20/03/2024 | C4: Pessoal | D4: Benefícios | E4: Despesa 3 - Benefícios | F4: Zeta Consultoria | G4: 2378.9251 | H4: Operações | I4: CC-3754 | J4: Maria Silva | K4: Em Análise
A5: 4 | B5: 19/12/2024 | C5: Viagens | D5: Transporte | E5: Despesa 4 - Transporte | F5: Mu Airlines | G5: 3848.9468 | H5: Diretoria | I5: CC-8944 | J5: Carla Souza | K5: Rejeitado
A6: 5 | B6: 29/10/2024 | C6: Viagens | D6: Alimentação | E6: Despesa 5 - Alimentação | F6: Kappa Software | G6: 3358.7205 | H6: Financeiro | I6: CC-8970 | J6: Maria Silva | K6: Em Análise
A7: 6 | B7: 25/10/2024 | C7: Administrativo | D7: Jurídico | E7: Despesa 6 - Jurídico | F7: Gama Tecnologia | G7: 1635.7366 | H7: TI | I7: CC-5659 | J7: Pedro Oliveira | K7: Em Análise
A8: 7 | B8: 09/02/2024 | C8: Operacional | D8: Limpeza | E8: Despesa 7 - Limpeza | F8: Theta Energy | G8: 1823.3736 | H8: Financeiro | I8: CC-8258 | J8: Ana Costa | K8: Rejeitado
A9: 8 | B9: 06/09/2024 | C9: TI | D9: Software | E9: Despesa 8 - Software | F9: Xi Eventos | G9: 4452.0156 | H9: Marketing | I9: CC-1997 | J9: Pedro Oliveira | K9: Aprovado
A10: 9 | B10: 05/08/2024 | C10: TI | D10: Manutenção | E10: Despesa 9 - Manutenção | F10: Gama Tecnologia | G10: 2671.3545 | H10: Diretoria | I10: CC-6474 | J10: Carla Souza | K10: Em Análise
A11: 10 | B11: 08/03/2024 | C11: Operacional | D11: Manutenção | E11: Despesa 10 - Manutenção | F11: Tech Solutions Ltda | G11: 962.02501 | H11: Operações | I11: CC-1259 | J11: João Santos | K11: Rejeitado
A12: 11 | B12: 19/11/2024 | C12: Pessoal | D12: Benefícios | E12: Despesa 11 - Benefícios | F12: Tech Solutions Ltda | G12: 3434.8211 | H12: Diretoria | I12: CC-8029 | J12: Carla Souza | K12: Rejeitado
A13: 12 | B13: 15/07/2024 | C13: Pessoal | D13: Benefícios | E13: Despesa 12 - Benefícios | F13: Iota Telecom | G13: 3025.1432 | H13: Financeiro | I13: CC-2385 | J13: Carla Souza | K13: Pendente
... A56: 55 | B56: 17/08/2024 | C56: Pessoal | D56: Salários | E56: Despesa 55 - Salários | F56: Theta Energy | G56: 10720.065 | H56: TI | I56: CC-8331 | J56: Ana Costa | K56: Aprovado
A57: 56 | B57: 07/04/2024 | C57: Viagens | D57: Hospedagem | E57: Despesa 56 - Hospedagem | G57: 1080.6557 | H57: Vendas | I57: CC-6738 | J57: Ana Costa | K57: Em Análise
A58: 57 | B58: 15/06/2024 | C58: Infraestrutura | D58: Água | E58: Despesa 57 - Água | F58: Omicron Seguros | G58: 357.98699 | H58: Diretoria | I58: CC-9641 | J58: João Santos | K58: Aprovado
A59: 58 | B59: 21/08/2024 | C59: Operacional | D59: Materiais | E59: Despesa 58 - Materiais | F59: Delta Logistics | G59: 520.17635 | H59: RH | I59: CC-5351 | J59: Carla Souza | K59: Aprovado
A60: 59 | B60: 05/08/2024 | C60: Marketing | D60: Redes Sociais | E60: Despesa 59 - Redes Sociais | F60: Tech Solutions Ltda | G60: 1973.4428 | H60: Financeiro | I60: CC-7769 | J60: Carla Souza | K60: Em Análise
A61: 60 | B61: 05/10/2024 | C61: Pessoal | D61: Benefícios | E61: Despesa 60 - Benefícios | F61: Omicron Seguros | G61: 4764.0947 | H61: Operações | I61: CC-3924 | J61: João Santos | K61: Em Análise
A62: 61 | B62: 14/10/2024 | C62: Operacional | D62: Manutenção | E62: Despesa 61 - Manutenção | F62: Zeta Consultoria | G62: 2736.4428 | H62: RH | J62: Ana Costa | K62: Rejeitado
A63: 62 | B63: 21/04/2024 | C63: Infraestrutura | D63: Telefonia | E63: Despesa 62 - Telefonia | F63: Xi Eventos | G63: 4520.9219 | H63: Marketing | I63: CC-4101 | J63: Maria Silva | K63: Rejeitado
A64: 63 | B64: 24/06/2024 | C64: Infraestrutura | D64: Energia | E64: Despesa 63 - Energia | F64: Eta Supplies | G64: 2492.1504 | H64: Marketing | I64: CC-2901 | J64: Ana Costa | K64: Pendente
A65: 64 | B65: 23/03/2024 | C65: Marketing | D65: Eventos | E65: Despesa 64 - Eventos | F65: Eta Supplies | G65: 3296.7857 | H65: RH | I65: CC-8750 | J65: João Santos | K65: Pendente
A66: 65 | B66: 19/05/2024 | C66: Infraestrutura | D66: Energia | E66: Despesa 65 - Energia | F66: Zeta Consultoria | G66: 2834.4972 | H66: Vendas | I66: CC-9917 | J66: Carla Souza | K66: Em Análise
A67: 66 | B67: 12/01/2024 | C67: Administrativo | D67: Jurídico | E67: Despesa 66 - Jurídico | F67: Iota Telecom | G67: 3535.6937 | H67: RH | I67: CC-3525 | J67: Maria Silva | K67: Pendente
A68: 67 | B68: 2024-15-32 | C68: Administrativo | D68: Jurídico | E68: Despesa 67 - Jurídico | F68: Gama Tecnologia | G68: 2991.2814 | H68: Diretoria | I68: CC-7294 | J68: João Santos | K68: Em Análise
A69: 68 | B69: 02/07/2024 | C69: TI | D69: Manutenção | E69: Despesa 68 - Manutenção | F69: Eta Supplies | G69: 1816.0487 | H69: TI | I69: CC-8962 | J69: Carla Souza | K69: Em Análise
A70: 69 | B70: 08/10/2024 | C70: Marketing | D70: Publicidade Online | E70: Despesa 69 - Publicidade Online | F70: Tech Solutions Ltda | G70: 3363.2027 | H70: Financeiro | I70: CC-8301 | J70: Pedro Oliveira | K70: Aprovado
A71: 70 | B71: 17/10/2024 | C71: Administrativo | D71: Seguros | E71: Despesa 70 - Seguros | F71: Alpha Serviços | G71: 4762.2634 | H71: TI | I71: CC-3832 | J71: Maria Silva | K71: Aprovado
A72: 71 | B72: 16/09/2024 | C72: Pessoal | D72: Treinamento | E72: Despesa 71 - Treinamento | F72: Gama Tecnologia | G72: 1184.9042 | H72: Operações | I72: CC-1425 | J72: Maria Silva | K72: Rejeitado
A73: 72 | B73: 28/10/2024 | C73: Administrativo | D73: Jurídico | E73: Despesa 72 - Jurídico | F73: Epsilon Marketing | G73: 2891.8699 | H73: Financeiro | I73: CC-8787 | J73: Ana Costa | K73: Em Análise
A74: 73 | B74: 22/08/2024 | C74: Infraestrutura | D74: Água | E74: Despesa 73 - Água | F74: Tech Solutions Ltda | G74: 968.15432 | H74: Operações | I74: CC-4262 | J74: João Santos | K74: Em Análise
... A112: 111 | B112: 05/04/2024 | C112: Marketing | D112: Eventos | E112: Despesa 111 - Eventos | F112: Xi Eventos | G112: 409.94597 | H112: TI | I112: CC-2139 | J112: João Santos | K112: Em Análise
A113: 112 | B113: 10/08/2024 | C113: Viagens | D113: Transporte | E113: Despesa 112 - Transporte | G113: 384.54567 | H113: Financeiro | I113: CC-3487 | J113: Carla Souza | K113: Em Análise
A114: 113 | B114: 24/08/2024 | C114: Operacional | D114: Limpeza | E114: Despesa 113 - Limpeza | F114: Mu Airlines | G114: 1836.8015 | H114: Diretoria | I114: CC-5577 | J114: Maria Silva | K114: Rejeitado
A115: 114 | B115: 28/04/2024 | C115: Operacional | D115: Manutenção | E115: Despesa 114 - Manutenção | F115: Theta Energy | G115: 3892.1883 | H115: Marketing | I115: CC-4365 | J115: Carla Souza | K115: Em Análise
A116: 115 | B116: 17/10/2024 | C116: Viagens | D116: Transporte | E116: Despesa 115 - Transporte | F116: Omicron Seguros | G116: 1539.2785 | H116: Operações | I116: CC-1357 | J116: Ana Costa | K116: Aprovado
A117: 116 | B117: 12/06/2024 | C117: Operacional | D117: Manutenção | E117: Despesa 116 - Manutenção | F117: Lambda Hotels | G117: 4979.226 | H117: TI | I117: CC-3252 | J117: João Santos | K117: Aprovado
A118: 117 | B118: 20/12/2024 | C118: Marketing | D118: Material Gráfico | E118: Despesa 117 - Material Gráfico | F118: Mu Airlines | G118: 994.16483 | H118: Diretoria | I118: CC-8280 | J118: Carla Souza | K118: Em Análise
A119: 118 | B119: 16/03/2024 | C119: Marketing | D119: Publicidade Online | E119: Despesa 118 - Publicidade Online | F119: Beta Comercial | G119: 6265.4213 | H119: Financeiro | J119: Ana Costa | K119: Em Análise
A120: 119 | B120: 05/07/2024 | C120: Administrativo | D120: Jurídico | E120: Despesa 119 - Jurídico | F120: Kappa Software | G120: 3393.2809 | H120: Operações | I120: CC-5652 | J120: Ana Costa | K120: Rejeitado
A121: 120 | B121: 09/09/2024 | C121: Infraestrutura | D121: Internet | E121: Despesa 120 - Internet | F121: Tech Solutions Ltda | G121: 2610.7041 | H121: Operações | I121: CC-5244 | J121: Pedro Oliveira | K121: Rejeitado
A122: 121 | B122: 05/01/2024 | C122: Infraestrutura | D122: Telefonia | E122: Despesa 121 - Telefonia | F122: Theta Energy | G122: 115.23426 | H122: RH | I122: CC-8978 | J122: João Santos | K122: Aprovado
A123: 122 | B123: 02/08/2024 | C123: Operacional | D123: Materiais | E123: Despesa 122 - Materiais | F123: Delta Logistics | G123: 1357.0003 | H123: Vendas | I123: CC-3910 | J123: Pedro Oliveira | K123: Pendente
A124: 123 | C124: Operacional | D124: Manutenção | E124: Despesa 123 - Manutenção | F124: Epsilon Marketing | G124: 731.16857 | H124: Diretoria | I124: CC-8285 | J124: Maria Silva | K124: Pendente
A125: 124 | B125: 03/07/2024 | C125: TI | D125: Software | E125: Despesa 124 - Software | F125: Delta Logistics | G125: 1894.7738 | H125: Operações | I125: CC-7789 | J125: Pedro Oliveira | K125: Rejeitado
A126: 125 | B126: 20/05/2024 | C126: Infraestrutura | D126: Telefonia | E126: Despesa 125 - Telefonia | F126: Zeta Consultoria | G126: 4297.5368 | H126: Operações | I126: CC-8049 | J126: Pedro Oliveira | K126: Rejeitado
A127: 126 | B127: 07/08/2024 | C127: Operacional | D127: Limpeza | E127: Despesa 126 - Limpeza | F127: Zeta Consultoria | G127: 846.56747 | H127: Diretoria | I127: CC-7417 | J127: João Santos | K127: Em Análise
A128: 127 | B128: 23/03/2024 | C128: Viagens | D128: Alimentação | E128: Despesa 127 - Alimentação | F128: Epsilon Marketing | G128: 266.30086 | H128: Financeiro | I128: CC-6358 | J128: Maria Silva | K128: Rejeitado
A129: 128 | B129: 19/12/2024 | C129: Marketing | D129: Redes Sociais | E129: Despesa 128 - Redes Sociais | F129: Alpha Serviços | G129: 2879.9201 | H129: Financeiro | I129: CC-1798 | J129: Pedro Oliveira | K129: Aprovado
A130: 129 | B130: 01/03/2024 | C130: Infraestrutura | D130: Energia | E130: Despesa 129 - Energia | F130: Omicron Seguros | G130: 501.35475 | H130: TI | I130: CC-4629 | J130: Maria Silva | K130: Em Análise
A131: 130 | B131: 18/12/2024 | C131: Pessoal | D131: Treinamento | E131: Despesa 130 - Treinamento | F131: Iota Telecom | G131: 3053.0604 | H131: Diretoria | I131: CC-8986 | J131: João Santos | K131: Rejeitado
A132: 131 | B132: 10/11/2024 | C132: Infraestrutura | D132: Energia | E132: Despesa 131 - Energia | F132: Tech Solutions Ltda | G132: 2659.2197 | H132: Diretoria | I132: CC-8815 | J132: João Santos | K132: Em Análise
A133: 132 | B133: 11/01/2024 | C133: Marketing | D133: Material Gráfico | E133: Despesa 132 - Material Gráfico | F133: Eta Supplies | G133: 760.87518 | H133: Marketing | I133: CC-2956 | J133: João Santos | K133: Em Análise
A134: 133 | B134: 06/05/2024 | C134: Marketing | D134: Eventos | E134: Despesa 133 - Eventos | F134: Eta Supplies | G134: 1971.6043 | H134: Operações | I134: CC-1074 | J134: Maria Silva | K134: Pendente
A135: 134 | B135: 13/01/2024 | C135: Pessoal | D135: Benefícios | E135: Despesa 134 - Benefícios | F135: Xi Eventos | G135: -1204.172 | H135: RH | I135: CC-8452 | J135: Maria Silva | K135: Em Análise
A136: 135 | B136: 08/09/2024 | C136: Administrativo | D136: Jurídico | E136: Despesa 135 - Jurídico | F136: Nu Transportes | G136: 884.1501 | H136: TI | I136: CC-2408 | J136: Ana Costa | K136: Aprovado
... A145: 144 | B145: 14/09/2024 | C145: Marketing | D145: Material Gráfico | E145: Despesa 144 - Material Gráfico | F145: Kappa Software | G145: 2561.0277 | H145: Marketing | I145: CC-2913 | J145: João Santos | K145: Em Análise
A146: 145 | B146: 10/04/2024 | D146: N/A | E146: Despesa 145 - N/A | F146: Zeta Consultoria | G146: 1460.9427 | H146: TI | I146: CC-3835 | J146: Carla Souza | K146: Em Análise
A147: 146 | B147: 29/04/2024 | C147: Administrativo | D147: Jurídico | E147: Despesa 146 - Jurídico | F147: Epsilon Marketing | G147: 2431.8415 | H147: Operações | I147: CC-5681 | J147: Carla Souza | K147: Rejeitado
A148: 147 | B148: 22/08/2024 | C148: Pessoal | D148: Salários | E148: Despesa 147 - Salários | F148: Omicron Seguros | G148: 3426.4301 | H148: Financeiro | I148: CC-2086 | J148: Ana Costa | K148: Rejeitado
A149: 148 | B149: 03/10/2024 | C149: Viagens | D149: Hospedagem | E149: Despesa 148 - Hospedagem | F149: Nu Transportes | G149: 4529.8278 | H149: Operações | I149: CC-7823 | J149: João Santos | K149: Pendente
A150: 149 | B150: 10/06/2024 | C150: Pessoal | D150: Salários | E150: Despesa 149 - Salários | F150: Eta Supplies | G150: 5652.537 | H150: Marketing | I150: CC-2823 | J150: Ana Costa | K150: Aprovado
A151: 150 | B151: 20/05/2024 | C151: Operacional | D151: Manutenção | E151: Despesa 150 - Manutenção | F151: Gama Tecnologia | G151: 2134.2585 | H151: Vendas | I151: CC-5085 | J151: Ana Costa | K151: Pendente
A152: 151 | B152: 09/11/2024 | C152: Viagens | D152: Hospedagem | E152: Despesa 151 - Hospedagem | F152: Omicron Seguros | G152: 1433.5753 | H152: Financeiro | I152: CC-5178 | J152: João Santos | K152: Em Análise
A153: 152 | B153: 16/09/2024 | C153: TI | D153: Software | E153: Despesa 152 - Software | F153: Nu Transportes | G153: 4112.2217 | H153: RH | I153: CC-1293 | J153: João Santos | K153: Aprovado
A154: 153 | B154: 10/04/2024 | C154: Viagens | D154: Alimentação | E154: Despesa 153 - Alimentação | F154: Gama Tecnologia | G154: 0 | H154: TI | I154: CC-4760 | J154: Carla Souza | K154: Rejeitado
A155: 154 | B155: 14/08/2024 | C155: Administrativo | D155: Papelaria | E155: Despesa 154 - Papelaria | F155: Iota Telecom | G155: 3569.9833 | H155: Operações | I155: CC-4120 | J155: João Santos | K155: Em Análise
A156: 155 | B156: 29/04/2024 | C156: Administrativo | D156: Papelaria | E156: Despesa 155 - Papelaria | F156: Mu Airlines | G156: 3856.8263 | H156: Vendas | I156: CC-9718 | J156: Carla Souza | K156: Aprovado
A157: 155 | B157: 25/12/2024 | C157: Marketing | D157: Eventos | E157: Despesa 155 - Eventos | F157: Iota Telecom | G157: 2510.7378 | H157: Operações | I157: CC-4081 | J157: Ana Costa | K157: Pendente
A158: 157 | B158: 09/04/2024 | C158: Viagens | D158: Transporte | E158: Despesa 157 - Transporte | F158: Mu Airlines | G158: 1190.7999 | H158: RH | I158: CC-6078 | J158: Pedro Oliveira | K158: Rejeitado
... A172: 171 | B172: 13/09/2024 | C172: Pessoal | D172: Salários | E172: Despesa 171 - Salários | F172: Alpha Serviços | G172: 4889.8677 | H172: Financeiro | I172: CC-6993 | J172: Carla Souza | K172: Em Análise
A173: 172 | B173: 06/12/2024 | C173: Viagens | D173: Passagens | E173: Despesa 172 - Passagens | F173: Iota Telecom | G173: 3026.6617 | H173: Operações | J173: Ana Costa | K173: Pendente
A174: 173 | B174: 01/05/2024 | C174: Infraestrutura | D174: Telefonia | E174: Despesa 173 - Telefonia | F174: Theta Energy | G174: 3043.7206 | H174: Vendas | I174: CC-4374 | J174: Carla Souza | K174: Em Análise
A175: 174 | B175: 22/09/2024 | C175: Administrativo | D175: Seguros | E175: Despesa 174 - Seguros | F175: Epsilon Marketing | G175: 1438.2019 | H175: RH | I175: CC-8296 | J175: Carla Souza | K175: Pendente
A176: 175 | B176: 29/01/2024 | C176: Marketing | D176: Publicidade Online | E176: Despesa 175 - Publicidade Online | F176: Omicron Seguros | G176: 8249.7385 | H176: RH | I176: CC-3190 | J176: Maria Silva | K176: Aprovado
A177: 176 | B177: 11/03/2024 | C177: Pessoal | D177: Recrutamento | E177: Despesa 176 - Recrutamento | F177: Tech Solutions Ltda | G177: 1016.068 | H177: Diretoria | I177: CC-5467 | J177: Pedro Oliveira | K177: Rejeitado
A178: 177 | B178: 03/11/2024 | C178: Administrativo | D178: Seguros | E178: Despesa 177 - Seguros | F178: Gama Tecnologia | G178: 735.86274 | H178: Vendas | I178: CC-5160 | J178: Ana Costa | K178: Aprovado
A179: 178 | B179: 07/01/2024 | C179: Pessoal | D179: Treinamento | E179: Despesa 178 - Treinamento | G179: 2618.2457 | H179: TI | I179: CC-2003 | J179: Carla Souza | K179: Rejeitado
A180: 179 | B180: 18/02/2024 | C180: Infraestrutura | D180: Aluguel | E180: Despesa 179 - Aluguel | F180: Alpha Serviços | G180: 19612.649 | H180: Operações | I180: CC-6326 | J180: Pedro Oliveira | K180: Rejeitado
A181: 180 | B181: 30/01/2024 | C181: Viagens | D181: Alimentação | E181: Despesa 180 - Alimentação | F181: Beta Comercial | G181: 3546.7863 | H181: TI | I181: CC-2261 | J181: Carla Souza | K181: Em Análise
A182: 181 | B182: 13/01/2024 | C182: Administrativo | D182: Jurídico | E182: Despesa 181 - Jurídico | F182: Lambda Hotels | G182: 2874.4125 | H182: RH | I182: CC-8557 | J182: Carla Souza | K182: Aprovado
A183: 182 | B183: 14/07/2024 | C183: Viagens | D183: Hospedagem | E183: Despesa 182 - Hospedagem | F183: Gama Tecnologia | G183: 4766.2869 | H183: Operações | I183: CC-6027 | J183: Maria Silva | K183: Pendente
A184: 183 | B184: 14/06/2024 | C184: Pessoal | D184: Salários | E184: Despesa 183 - Salários | F184: Eta Supplies | G184: 13314.721 | H184: Operações | I184: CC-7709 | J184: Pedro Oliveira | K184: Em Análise
A185: 184 | B185: 17/06/2024 | C185: Infraestrutura | D185: Energia | E185: Despesa 184 - Energia | F185: Beta Comercial | G185: 2945.396 | H185: TI | I185: CC-9661 | J185: Ana Costa | K185: Rejeitado
A186: 185 | B186: 12/07/2024 | C186: Infraestrutura | D186: Internet | E186: Despesa 185 - Internet | F186: Zeta Consultoria | G186: 4619.9776 | H186: Financeiro | I186: CC-8352 | J186: Carla Souza | K186: Em Análise
A187: 186 | B187: 10/06/2024 | C187: Infraestrutura | D187: Telefonia | E187: Despesa 186 - Telefonia | F187: Lambda Hotels | G187: 1633.7961 | H187: Operações | I187: CC-9916 | J187: João Santos | K187: Em Análise
A188: 187 | B188: 21/03/2024 | C188: Marketing | D188: Eventos | E188: Despesa 187 - Eventos | F188: Gama Tecnologia | G188: 2366.473 | H188: RH | I188: CC-2220 | J188: João Santos | K188: Rejeitado
A189: 188 | B189: 02/01/2024 | C189: Viagens | D189: Hospedagem | E189: Despesa 188 - Hospedagem | F189: Beta Comercial | G189: 4939.1581 | H189: TI | I189: CC-7589 | J189: João Santos | K189: Pendente
A190: 189 | B190: 22/05/2024 | C190: Infraestrutura | D190: Internet | E190: Despesa 189 - Internet | F190: Alpha Serviços | G190: -3454.5815 | H190: Marketing | I190: CC-9563 | J190: Carla Souza | K190: Aprovado
A191: 190 | B191: 07/06/2024 | C191: Infraestrutura | D191: Aluguel | E191: Despesa 190 - Aluguel | F191: Beta Comercial | G191: 16224.701 | H191: RH | I191: CC-1684 | J191: João Santos | K191: Rejeitado
... A201: 200 | B201: 28/07/2024 | C201: Infraestrutura | D201: Aluguel | E201: Despesa 200 - Aluguel | F201: Eta Supplies | G201: 10747.181 | H201: Marketing | I201: CC-1045 | J201: Carla Souza | K201: Rejeitado
F202: TOTAL: | G202: =SUM(G2:G201) -> 804686.9
F203: Média: | G203: =AVERAGE(G2:Z999) -> #VALUE!

Sheet Resumo por Categoria
A1: Categoria | B1: Total Despesas | C1: Qtd. Lançamentos | D1: Média | E1: % do Total
A2: Pessoal | B2: =SUMIF('Despesas 2024'!C:C,"Pessoal",'Despesas 2024'!G:G) -> 137361.08 | C2: =COUNTIF('Despesas 2024'!C:C,"Pessoal") -> 32 | D2: =B2/C2 -> 4292.5337 | E2: =B2/'Despesas 2024'!$G$202 -> 0.17070127
A3: Infraestrutura | B3: =SUMIF('Despesas 2024'!C:C,"Infraestrutura",'Despesas 2024'!G:G) -> 194535.09 | C3: =COUNTIF('Despesas 2024'!C:C,"Infraestrutura") -> 39 | D3: =B3/C3 -> 4988.0792 | E3: =B3/'Despesas 2024'!$G$202 -> 0.24175252
A4: Marketing | B4: =SUMIF('Despesas 2024'!C:C,"Marketing",'Despesas 2024'!G:G) -> 70415.662 | C4: =COUNTIF('Despesas 2024'!C:C,"Marketing") -> 24 | D4: =B4/C4 -> 2933.9859 | E4: =B4/'Despesas 2024'!$G$202 -> 0.087506907
A5: TI | B5: =SUMIF('Despesas 2024'!C:C,"TI",'Despesas 2024'!G:G) -> 44734.491 | C5: =COUNTIF('Despesas 2024'!C:C,"TI") -> 19 | D5: =B5/C5 -> 2354.4469 | E5: =B5/'Despesas 2024'!$G$202 -> 0.055592418
A6: Operacional | B6: =SUMIF('Despesas 2024'!C:C,"Operacional",'Despesas 2024'!G:G) -> 42521.28 | C6: =COUNTIF('Despesas 2024'!C:C,"Operacional") -> 22 | D6: =B6/C6 -> 1932.7855 | E6: =B6/'Despesas 2024'!$G$202 -> 0.052842019
A7: Administrativo | B7: =SUMIF('Despesas 2024'!C:C,"Administrativo",'Despesas 2024'!G:G) -> 157144.87 | C7: =COUNTIF('Despesas 2024'!C:C,"Administrativo") -> 29 | D7: =B7/C7 -> 5418.7887 | E7: =B7/'Despesas 2024'!$G$202 -> 0.19528698
A8: Viagens | B8: =SUMIF('Despesas 2024'!C:C,"Viagens",'Despesas 2024'!G:G) -> 155534.95 | C8: =COUNTIF('Despesas 2024'!C:C,"Viagens") -> 33 | D8: =B8/C8 -> 4713.1804 | E8: =B8/'Despesas 2024'!$G$202 -> 0.1932863
